teson/__init__.py
teson/converter.py
teson/exceptions.py
tests/examples.py
tests/generate_flat_data.py
tests/generate_nested_data.py
tests/test_llm_actual.py
tests/test_token_costs.py
teson-0.1.4.dist-info/METADATA
teson-0.1.4.dist-info/WHEEL
teson-0.1.4.dist-info/top_level.txt
teson-0.1.4.dist-info/RECORD
