Metadata-Version: 2.4
Name: teson
Version: 0.1.4
Summary: Python library for converting arbitrary JSON data structures to Token-efficient CSV format
Author-email: Jayed <jayedbinjahangir@gmail.com>
License-Expression: MIT AND (Apache-2.0 OR BSD-2-Clause)
Project-URL: Homepage, https://github.com/jayeeed/teson
Requires-Python: >=3.9
